FlaUILibrary/__init__.py
FlaUILibrary/pythonnetwrapper.py
FlaUILibrary/version.py
FlaUILibrary/bin/FlaUI.Core.dll
FlaUILibrary/bin/FlaUI.UIA2.dll
FlaUILibrary/bin/FlaUI.UIA3.dll
FlaUILibrary/bin/Interop.UIAutomationClient.dll
FlaUILibrary/bin/System.CodeDom.dll
FlaUILibrary/flaui/automation/uia.py
FlaUILibrary/flaui/automation/uia2.py
FlaUILibrary/flaui/automation/uia3.py
FlaUILibrary/flaui/enum/interfacetype.py
FlaUILibrary/flaui/enum/treeitemaction.py
FlaUILibrary/flaui/exception/flauierror.py
FlaUILibrary/flaui/interface/moduleinterface.py
FlaUILibrary/flaui/interface/valuecontainer.py
FlaUILibrary/flaui/interface/windowsautomationinterface.py
FlaUILibrary/flaui/module/application.py
FlaUILibrary/flaui/module/button.py
FlaUILibrary/flaui/module/checkbox.py
FlaUILibrary/flaui/module/combobox.py
FlaUILibrary/flaui/module/debug.py
FlaUILibrary/flaui/module/element.py
FlaUILibrary/flaui/module/grid.py
FlaUILibrary/flaui/module/keyboard.py
FlaUILibrary/flaui/module/mouse.py
FlaUILibrary/flaui/module/property.py
FlaUILibrary/flaui/module/screenshot.py
FlaUILibrary/flaui/module/selector.py
FlaUILibrary/flaui/module/tab.py
FlaUILibrary/flaui/module/textbox.py
FlaUILibrary/flaui/module/tooglebutton.py
FlaUILibrary/flaui/module/tree.py
FlaUILibrary/flaui/module/window.py
FlaUILibrary/flaui/util/automationelement.py
FlaUILibrary/flaui/util/automationinterfacecontainer.py
FlaUILibrary/flaui/util/converter.py
FlaUILibrary/flaui/util/keyboardinputconverter.py
FlaUILibrary/flaui/util/treeitems.py
FlaUILibrary/flaui/util/treeitemsparser.py
FlaUILibrary/keywords/application.py
FlaUILibrary/keywords/button.py
FlaUILibrary/keywords/checkbox.py
FlaUILibrary/keywords/combobox.py
FlaUILibrary/keywords/debug.py
FlaUILibrary/keywords/element.py
FlaUILibrary/keywords/grid.py
FlaUILibrary/keywords/keyboard.py
FlaUILibrary/keywords/listbox.py
FlaUILibrary/keywords/mouse.py
FlaUILibrary/keywords/property.py
FlaUILibrary/keywords/radiobutton.py
FlaUILibrary/keywords/screenshot.py
robotframework_flaui-4.0.5.dist-info/licenses/LICENSE
robotframework_flaui-4.0.5.dist-info/METADATA
robotframework_flaui-4.0.5.dist-info/WHEEL
robotframework_flaui-4.0.5.dist-info/top_level.txt
robotframework_flaui-4.0.5.dist-info/RECORD
