Metadata-Version: 2.4
Name: robotframework-flaui
Version: 4.0.5
Summary: Windows GUI testing library for Robot Framework
Author-email: G DATA CyberDefense AG <opensource@gdata.de>
License: MIT
Project-URL: Homepage, https://github.com/GDATASoftwareAG/robotframework-flaui
Platform: Windows
Classifier: Programming Language :: Python :: 3
Classifier: Programming Language :: Python :: 3.8
Classifier: Programming Language :: Python :: 3.9
Classifier: Programming Language :: Python :: 3.10
Classifier: Programming Language :: Python :: 3.11
Classifier: Programming Language :: Python :: 3.12
Classifier: Programming Language :: Python :: 3.13
Classifier: Operating System :: Microsoft :: Windows
Classifier: Topic :: Software Development :: Testing
Classifier: Framework :: Robot Framework
Classifier: Framework :: Robot Framework :: Library
License-File: LICENSE
Requires-Dist: robotframework>=3.2.2
Requires-Dist: typing-extensions>=3.10.0.0
Requires-Dist: robotframework-pythonlibcore>=3.0.0
Requires-Dist: pythonnet==3.0.*
Dynamic: license
Dynamic: license-file
Dynamic: platform
